__init__.py
playpty/__init__.py
playpty/__main__.py
playpty/playpty.py
playpty-0.4.1.dist-info/LICENSE
playpty-0.4.1.dist-info/METADATA
playpty-0.4.1.dist-info/WHEEL
playpty-0.4.1.dist-info/entry_points.txt
playpty-0.4.1.dist-info/top_level.txt
playpty-0.4.1.dist-info/RECORD
