Metadata-Version: 2.1
Name: playpty
Version: 0.4.1
Summary: Play script in pty
Author-email: wzshiming <wzshiming@foxmail.com>
License: MIT License
Project-URL: Homepage, https://github.com/wzshiming/playpty
Project-URL: Source, https://github.com/wzshiming/playpty
Keywords: playpty
Classifier: Development Status :: 3 - Alpha
Classifier: Intended Audience :: Developers
Classifier: License :: OSI Approved :: MIT License
Classifier: Programming Language :: Python :: 3
Classifier: Programming Language :: Python :: 3.9
Classifier: Programming Language :: Python :: 3.10
Classifier: Programming Language :: Python :: 3.11
Classifier: Programming Language :: Python :: 3.12
Classifier: Programming Language :: Python :: 3 :: Only
Requires-Python: >=3.9
License-File: LICENSE
